django_utils/__init__.py
django_utils/admin.py
django_utils/middleware.py
inspired_django_utils-0.3.dist-info/METADATA
inspired_django_utils-0.3.dist-info/RECORD
inspired_django_utils-0.3.dist-info/WHEEL
inspired_django_utils-0.3.dist-info/top_level.txt
