Metadata-Version: 2.1
Name: inspired-django-utils
Version: 0.3
Summary: A collection of Django utils
Home-page: https://github.com/inspired-solutions/django-utils
Author: Sergio Melendez
Author-email: hlpse@hotmail.com
License: MIT License
Platform: UNKNOWN
Classifier: Environment :: Web Environment
Classifier: Framework :: Django
Classifier: Framework :: Django :: 1.9
Classifier: Framework :: Django :: 2.0
Classifier: Intended Audience :: Developers
Classifier: License :: OSI Approved :: MIT License
Classifier: Operating System :: OS Independent
Classifier: Programming Language :: Python
Classifier: Programming Language :: Python :: 3.5
Classifier: Programming Language :: Python :: 3.6
Classifier: Topic :: Internet :: WWW/HTTP
Classifier: Topic :: Internet :: WWW/HTTP :: Dynamic Content
Requires-Dist: Django (<2.1,>=1.9)
Requires-Dist: djangorestframework (>=3.8)
